mqtt_sn_gateway/__init__.py
mqtt_sn_gateway/config.py
mqtt_sn_gateway/main.py
mqtt_sn_gateway/messages.py
mqtt_sn_gateway/server.py
mqtt_sn_gateway/topics.py
mqtt_sn_gateway-21.0.0.dist-info/LICENSE
mqtt_sn_gateway-21.0.0.dist-info/METADATA
mqtt_sn_gateway-21.0.0.dist-info/WHEEL
mqtt_sn_gateway-21.0.0.dist-info/entry_points.txt
mqtt_sn_gateway-21.0.0.dist-info/top_level.txt
mqtt_sn_gateway-21.0.0.dist-info/RECORD
