Metadata-Version: 2.1
Name: mqtt-sn-gateway
Version: 21.0.0
Summary: An async Python MQTT-SN Gayeway
Home-page: https://github.com/u9n/mqtt-sn-gateway
Author: Henrik Palmlund Wahlgren @ Palmlund Wahlgren Innovative Technology AB
Author-email: henrik@pwit.se
License: MIT
Platform: UNKNOWN
Classifier: Development Status :: 5 - Production/Stable
Classifier: License :: OSI Approved :: MIT License
Classifier: Natural Language :: English
Classifier: Programming Language :: Python
Classifier: Programming Language :: Python :: 3
Classifier: Programming Language :: Python :: 3 :: Only
Classifier: Programming Language :: Python :: 3.7
Classifier: Programming Language :: Python :: 3.8
Classifier: Programming Language :: Python :: 3.9
Classifier: Topic :: Software Development :: Libraries
Requires-Python: >=3.7
License-File: LICENSE
Requires-Dist: attrs
Requires-Dist: click
Requires-Dist: asyncio-mqtt
Requires-Dist: asyncio-dgram
Requires-Dist: uvloop
